setup.py
Beheaded/__init__.py
Beheaded.egg-info/PKG-INFO
Beheaded.egg-info/SOURCES.txt
Beheaded.egg-info/dependency_links.txt
Beheaded.egg-info/requires.txt
Beheaded.egg-info/top_level.txt