Metadata-Version: 1.1
Name: Beheaded
Version: 1.0
Summary: Generic X window and recording for headless setups in Python.
Home-page: https://github.com/mfalesni/Beheaded
Author: Milan Falešník
Author-email: milan@falesnik.net
License: GPLv2
Keywords: headless xvfb ffmpeg recording
Platform: UNKNOWN
Classifier: Topic :: Utilities
Classifier: License :: OSI Approved :: GNU General Public License v2 (GPLv2)
Classifier: Topic :: Software Development :: Quality Assurance
Classifier: Topic :: Internet :: WWW/HTTP :: Browsers
Classifier: Topic :: Multimedia :: Sound/Audio :: Capture/Recording
